harryplotter/__init__.py
harryplotter/model.py
harryplotter-0.1.0.dist-info/licenses/LICENSE
harryplotter-0.1.0.dist-info/METADATA
harryplotter-0.1.0.dist-info/WHEEL
harryplotter-0.1.0.dist-info/top_level.txt
harryplotter-0.1.0.dist-info/RECORD
