Metadata-Version: 2.4
Name: harryplotter
Version: 0.1.0
Summary: A simple machine learning package using scikit-learn
Author-email: RahulSwami <abeotttyy@gmail.com>
License: RahulSwami
Project-URL: Homepage, https://github.com/RahulSwami01/Harryplotter
Requires-Python: >=3.6
License-File: LICENSE
Requires-Dist: scikit-learn>=1.0
Dynamic: license-file
